setup.py
bin/ex_timer
ex_timer/__init__.py
ex_timer/ex_timer.py
ex_timer.egg-info/PKG-INFO
ex_timer.egg-info/SOURCES.txt
ex_timer.egg-info/dependency_links.txt
ex_timer.egg-info/top_level.txt